covmapy/__init__.py
covmapy/cli.py
covmapy/color.py
covmapy/constants.py
covmapy/core.py
covmapy/exceptions.py
covmapy/models.py
covmapy/parser.py
covmapy/plotly_treemap.py
covmapy-0.2.0.dist-info/METADATA
covmapy-0.2.0.dist-info/WHEEL
covmapy-0.2.0.dist-info/entry_points.txt
covmapy-0.2.0.dist-info/licenses/LICENSE
covmapy-0.2.0.dist-info/RECORD
