Metadata-Version: 2.4
Name: covmapy
Version: 0.2.0
Summary: Coverage visualization tool that generates interactive treemaps
License: MIT
License-File: LICENSE
Requires-Python: >=3.9
Requires-Dist: click<9.0,>=8.0
Requires-Dist: plotly<8.0,>=5.0
